chatlogger/__init__.py
chatlogger/logger.py
chatlogger-0.1.0.dist-info/METADATA
chatlogger-0.1.0.dist-info/WHEEL
chatlogger-0.1.0.dist-info/top_level.txt
chatlogger-0.1.0.dist-info/RECORD
