Metadata-Version: 2.1
Name: chatlogger
Version: 0.1.0
Summary: Log your OpenAI conversations locally
Author: Esha Manideep
Author-email: esha@giga.do
